{
  "openapi": "3.0.1",
  "info": {
    "title": "API de AutenticacionMS",
    "description": "Documentación de la API de AutenticacionMS",
    "version": "1.0"
  },
  "servers": [
    {
      "url": "http://localhost:8080/authenticationms",
      "description": "Generated server url"
    }
  ],
  "paths": {
    "/auth/refresh-token": {
      "post": {
        "tags": [
          "auth-controller"
        ],
        "operationId": "refreshToken",
        "requestBody": {
          "content": {
            "application/json": {
              "schema": {
                "$ref": "#/components/schemas/JwtRefreshRequest"
              }
            }
          },
          "required": true
        },
        "responses": {
          "200": {
            "description": "OK",
            "content": {
              "*/*": {
                "schema": {
                  "$ref": "#/components/schemas/JwtResponse"
                }
              }
            }
          }
        }
      }
    },
    "/auth/login": {
      "post": {
        "tags": [
          "auth-controller"
        ],
        "operationId": "createAuthenticationToken",
        "requestBody": {
          "content": {
            "application/json": {
              "schema": {
                "$ref": "#/components/schemas/JwtRequest"
              }
            }
          },
          "required": true
        },
        "responses": {
          "200": {
            "description": "OK",
            "content": {
              "*/*": {
                "schema": {
                  "$ref": "#/components/schemas/JwtResponse"
                }
              }
            }
          }
        }
      }
    }
  },
  "components": {
    "schemas": {
      "JwtRefreshRequest": {
        "type": "object",
        "properties": {
          "refreshToken": {
            "type": "string"
          }
        }
      },
      "JwtResponse": {
        "type": "object",
        "properties": {
          "token": {
            "type": "string"
          },
          "refreshToken": {
            "type": "string"
          },
          "message": {
            "type": "string"
          }
        }
      },
      "JwtRequest": {
        "type": "object",
        "properties": {
          "email": {
            "type": "string"
          },
          "password": {
            "type": "string"
          }
        }
      }
    }
  }
}
